zondocs_theme/__init__.py
zondocs_theme/action.html
zondocs_theme/breadcrumbs.html
zondocs_theme/footer.html
zondocs_theme/layout.html
zondocs_theme/logo.html
zondocs_theme/searchbox.html
zondocs_theme/theme.conf
zondocs_theme/static/builddate.js_t
zondocs_theme/static/navbutton.js
zondocs_theme/static/navigation.js
zondocs_theme/static/theme.css
zondocs_theme-1.0.8.dist-info/LICENSE
zondocs_theme-1.0.8.dist-info/METADATA
zondocs_theme-1.0.8.dist-info/WHEEL
zondocs_theme-1.0.8.dist-info/entry_points.txt
zondocs_theme-1.0.8.dist-info/top_level.txt
zondocs_theme-1.0.8.dist-info/RECORD
