Metadata-Version: 2.1
Name: zondocs-theme
Version: 1.0.8
Summary: Sphinx theme for ZEIT ONLINE docs
Author-email: Nico Bruenjes <nico.bruenjes@zeit.de>
Maintainer-email: Nico Bruenjes <nico.bruenjes@zeit.de>
License: MIT
Project-URL: Changes, https://github.com/ZeitOnline/zondocs_theme/blob/main/CHANGES.txt
Project-URL: Source Code, https://github.com/zeitonline/zondocs_theme/
Project-URL: Issue Tracker, https://github.com/zeitonline/zondocs_theme/issues/
Classifier: License :: OSI Approved :: MIT License
Classifier: Programming Language :: Python
Classifier: Programming Language :: Python :: 3
Classifier: Framework :: Sphinx
Classifier: Framework :: Sphinx :: Theme
Requires-Python: >=3.7
License-File: LICENSE
